upcase/__init__.py
upcase/upcf.py
uppercdevdev102218067-0.0.1.dist-info/METADATA
uppercdevdev102218067-0.0.1.dist-info/WHEEL
uppercdevdev102218067-0.0.1.dist-info/top_level.txt
uppercdevdev102218067-0.0.1.dist-info/RECORD
