Metadata-Version: 2.1
Name: uppercdevdev102218067
Version: 0.0.1
Summary: Uppercase package
Author: Devansh Arya
Author-email: <dv30arya@gmail.com>
Keywords: python
Classifier: Development Status :: 1 - Planning
Classifier: Intended Audience :: Developers
Classifier: Programming Language :: Python :: 3
Classifier: Operating System :: Unix
Classifier: Operating System :: MacOS :: MacOS X
Classifier: Operating System :: Microsoft :: Windows
